{
    "details": {
        "job_history": [
            {
                "role_name": "EXPRESSIVE ARTS PROGRAM LEADER",
                "work_description": "Formulated, proposed, and was authorized to implement 'The Arts Project,' a weekly therapeutic, expressive arts program for 10+ 'at-risk' CPS middle school students residing in a low-income urban neighborhood.",
                "company_level": "Unknown",
                "start_date": "09/2014",
                "end_date": "06/2015"
            },
            {
                "role_name": "EXPRESSIVE ARTS PROGRAM LEADER",
                "work_description": "Designed & delivered curriculum for weekly coping skills sessions with groups of 20-50 early adolescents & their mentors. Tailored sessions to address unique risk factors faced by our youth (e.g. community violence, chronic poverty, school dropout). Integrated therapeutic approaches from various evidence-based practices (DBT, CBT, Mindfulness-based Stress Reduction). Produced & administered usability, feasibility, and satisfaction forms for coping skills training attendees (staff, mentors, & mentees). Evaluated and amended curriculum based on youth, mentor, and staff feedback.",
                "company_level": "Unknown",
                "start_date": "09/2012",
                "end_date": "06/2014"
            },
            {
                "role_name": "MENTOR SUPERVISION TEAM LEADER & SUPERVISOR",
                "work_description": "Developed measures and organized platforms for more than 50 mentors to report contact with mentee. Conducted thorough interviews with potential mentors, youth participants, and parents of youth in the mentoring intervention so to arrange meaningful and lasting youth-mentor relationships. Supervised up to 8 mentor-mentee pairs at a time; monitored and documented all contact & activities between pairs. Combined forces with teachers and parents regularly to assess the needs of and establish protective resources for our youth. Organized weekly meetings with each supervisee to problem-solve, provide support, and address conflicts or concerns regarding their mentoring relationship.",
                "company_level": "Unknown",
                "start_date": "09/2012",
                "end_date": "08/2014"
            },
            {
                "role_name": "TEACHING ASSISTANT",
                "work_description": "Over the course of 6 academic terms, promoted engaging discussions, critical thinking, and a warm learning environment for groups of 50-60 undergraduate students enrolled in PSY-305 (a community-based service learning course). Was selected out of four graduate assistants to be 'Head Teaching Assistant' of the course throughout 2013-14 academic year.",
                "company_level": "Unknown",
                "start_date": "09/2012",
                "end_date": "06/2014"
            },
            {
                "role_name": "COMMUNITY LIVING SUPPORT PERSON",
                "work_description": "Guided individuals with developmental disabilities in achieving personal goals, overcoming barriers, & participating in activities of their choice; recorded progress on skill development and achievement. Served as a role model and mentor; demonstrated and coached social and behavioral skill development. Prompted & praised the use of independent living skills, such as cooking, money management, household shopping, doing laundry, & personal hygiene.",
                "company_level": "Unknown",
                "start_date": "06/2008",
                "end_date": "08/2011"
            }
        ],
        "education": [
            {
                "university": "DePaul University",
                "start_date": "Unknown",
                "end_date": "Present",
                "domain": "General Psychology Clinical Child",
                "level": "Master's"
            },
            {
                "university": "DePaul University",
                "start_date": "Unknown",
                "end_date": "2012",
                "domain": "General Psychology Human Development",
                "level": "Bachelor's"
            }
        ],
        "projects": [],
        "interests": [
            "Child Life Volunteer - Children's Memorial Hospital (2011-2012)",
            "United Way Volunteer - Hearts of West Michigan (2009)",
            "Animal Shelter Volunteer - Kent County Animal Shelter (2008)",
            "Summer Camp Volunteer - SpringHill Camps (2005-2006)"
        ]
    },
    "skills": {
        "skills": [
            {
                "name": "Program Development",
                "level": 4,
                "explanation": "Formulated, proposed, and implemented 'The Arts Project,' a weekly therapeutic, expressive arts program, and designed & delivered curriculum for weekly coping skills sessions, demonstrating strong proficiency."
            },
            {
                "name": "Leadership",
                "level": 4,
                "explanation": "Held leadership roles such as EXPRESSIVE ARTS PROGRAM LEADER and MENTOR SUPERVISION TEAM LEADER & SUPERVISOR, supervising teams and mentoring individuals, indicating strong proficiency."
            },
            {
                "name": "Mentorship",
                "level": 4,
                "explanation": "Supervised up to 8 mentor-mentee pairs at a time, monitored and documented all contact & activities between pairs, and conducted thorough interviews with potential mentors, demonstrating strong proficiency."
            },
            {
                "name": "Teaching",
                "level": 3,
                "explanation": "Promoted engaging discussions, critical thinking, and a warm learning environment for groups of 50-60 undergraduate students, showing a solid working proficiency."
            },
            {
                "name": "Community Support",
                "level": 3,
                "explanation": "Guided individuals with developmental disabilities in achieving personal goals, overcoming barriers, & participating in activities of their choice, demonstrating a solid working proficiency."
            },
            {
                "name": "Volunteer Management",
                "level": 2,
                "explanation": "Participated in various volunteer roles, such as Child Life Volunteer, United Way Volunteer, Animal Shelter Volunteer, and Summer Camp Volunteer, showing some practical experience."
            },
            {
                "name": "Project Evaluation",
                "level": 3,
                "explanation": "Produced & administered usability, feasibility, and satisfaction forms for coping skills training attendees, and evaluated and amended curriculum based on feedback, demonstrating a solid working proficiency."
            },
            {
                "name": "Communication",
                "level": 3,
                "explanation": "Combined forces with teachers and parents regularly to assess the needs of and establish protective resources for youth, and organized weekly meetings with each supervisee to problem-solve, provide support, and address conflicts or concerns, showing a solid working proficiency."
            }
        ]
    }
}