{
    "resume_file": "825.json",
    "output": {
        "working_experience": 24,
        "influence_factor_score": 7,
        "influence_factor_breakdown": {
            "job_role_level": 3,
            "company_size_and_influence": 2,
            "experience_and_tenure": 2
        },
        "notes": "The candidate's extensive experience and leadership roles result in a moderate influence factor score. However, the lack of information about the company size and influence limits the score."
    }
}