{
    "resume_file": "270.json",
    "output": {
        "working_experience": 10,
        "influence_factor_score": 8,
        "influence_factor_breakdown": {
            "job_role_level": 3,
            "company_size_and_influence": 3,
            "experience_and_tenure": 2
        },
        "notes": "The candidate's experience in various roles, including Consultant Project Manager, and their work in Large Corporation and Mid-level companies, results in a moderate to high influence factor score."
    }
}