{
    "resume_file": "74.json",
    "recommendation_file": "Recommendation_From_ID_236.txt",
    "output": {
        "relevance_score": 8,
        "fraud_chance_level": 1,
        "fraud_reason": "No red flags or statistically improbable claims detected. Language is formal.",
        "verified_skills": [
            "IT Management",
            "Technical Support",
            "Network Administration",
            "Software Management",
            "Microsoft Windows",
            "Mac OS X",
            "Linux",
            "Cisco Infrastructure"
        ],
        "recommendation_source": "Peer",
        "notes": "The recommendation aligns well with the candidate's skills and experience, providing specific examples of their IT management and technical support abilities. However, the recommender's background as an English Language Arts teacher may not provide direct insight into the candidate's technical expertise."
    }
}