{
    "target_id": "30",
    "recommendations": [
        {
            "recommender_id": "215",
            "recommendation": {
                "resume_file": "30.json",
                "recommendation_file": "Recommendation_From_ID_215.txt",
                "output": {
                    "relevance_score": 9,
                    "fraud_chance_level": 1,
                    "fraud_reason": "No red flags or statistically improbable claims detected. Language is formal.",
                    "verified_skills": [
                        "Project Management",
                        "Construction Management",
                        "Accounting",
                        "Contract Management",
                        "Budgeting",
                        "Leadership"
                    ],
                    "recommendation_source": "Peer",
                    "notes": "The recommendation aligns well with the candidate's skills and experience, providing specific examples of their project accounting and financial management expertise."
                }
            }
        },
        {
            "recommender_id": "643",
            "recommendation": {
                "resume_file": "30.json",
                "recommendation_file": "Recommendation_From_ID_643.txt",
                "output": {
                    "relevance_score": 8,
                    "fraud_chance_level": 2,
                    "fraud_reason": "The recommendation seems genuine, but the recommender's relationship to the candidate is unclear and the recommender's experience seems unrelated to the candidate's field.",
                    "verified_skills": [
                        "Project Management",
                        "Accounting"
                    ],
                    "recommendation_source": "Unknown",
                    "notes": "The recommendation highlights the candidate's project management and accounting skills, but the recommender's experience seems unrelated to the candidate's field, and their relationship to the candidate is unclear."
                }
            }
        },
        {
            "recommender_id": "152",
            "recommendation": {
                "resume_file": "30.json",
                "recommendation_file": "Recommendation_From_ID_152.txt",
                "output": {
                    "relevance_score": 8,
                    "fraud_chance_level": 1,
                    "fraud_reason": "No red flags or statistically improbable claims detected. Language is formal.",
                    "verified_skills": [
                        "Project Management",
                        "Construction Management",
                        "Accounting",
                        "Contract Management",
                        "Budgeting",
                        "Leadership"
                    ],
                    "recommendation_source": "Peer",
                    "notes": "The recommendation aligns well with the candidate's skills and experience, providing specific examples of their project accounting expertise and strong organizational skills."
                }
            }
        },
        {
            "recommender_id": "332",
            "recommendation": {
                "resume_file": "30.json",
                "recommendation_file": "Recommendation_From_ID_332.txt",
                "output": {
                    "relevance_score": 9,
                    "fraud_chance_level": 1,
                    "fraud_reason": "No red flags or statistically improbable claims detected. Language is formal.",
                    "verified_skills": [
                        "Project Management",
                        "Construction Management",
                        "Accounting",
                        "Contract Management",
                        "Budgeting"
                    ],
                    "recommendation_source": "Unknown",
                    "notes": "The recommendation aligns well with the candidate's skills and experience, providing specific examples of their project accounting and construction management expertise."
                }
            }
        },
        {
            "recommender_id": "430",
            "recommendation": {
                "resume_file": "30.json",
                "recommendation_file": "Recommendation_From_ID_430.txt",
                "output": {
                    "relevance_score": 9,
                    "fraud_chance_level": 1,
                    "fraud_reason": "No red flags or statistically improbable claims detected. Language is formal.",
                    "verified_skills": [
                        "Project Management",
                        "Construction Management",
                        "Accounting",
                        "Contract Management",
                        "Budgeting",
                        "Leadership"
                    ],
                    "recommendation_source": "Unknown",
                    "notes": "The recommendation aligns well with the candidate's skills and experience, providing specific examples of their project accounting and management abilities."
                }
            }
        }
    ]
}