{
    "target_id": "80",
    "recommendations": [
        {
            "recommender_id": "420",
            "recommendation": {
                "resume_id": 80,
                "recommendation_file": "Recommendation_From_ID_420.txt",
                "output": {
                    "relevance_score": 9,
                    "fraud_chance_level": 1,
                    "fraud_reason": "No red flags or statistically improbable claims detected. Language is formal.",
                    "verified_skills": [
                        "Technical Support",
                        "Customer Service",
                        "Troubleshooting",
                        "Communication"
                    ],
                    "recommendation_source": "Peer",
                    "notes": "The recommendation aligns well with the candidate's skills and experience, providing specific examples of their technical support and customer service abilities. The recommender's experience in a similar role adds credibility to the recommendation."
                }
            }
        },
        {
            "recommender_id": "680",
            "recommendation": {
                "resume_id": 80,
                "recommendation_file": "Recommendation_From_ID_680.txt",
                "output": {
                    "relevance_score": 8,
                    "fraud_chance_level": 2,
                    "fraud_reason": "The recommendation seems genuine, but the source is unclear and the language is slightly informal. No statistically improbable claims detected.",
                    "verified_skills": [
                        "Technical Support",
                        "Troubleshooting",
                        "Communication",
                        "Customer Service"
                    ],
                    "recommendation_source": "Unknown",
                    "notes": "The recommendation highlights the candidate's strengths in communication, analytical abilities, and technical support, which aligns with their skills and experience. However, the source of the recommendation is unclear, and the language is slightly informal."
                }
            }
        }
    ]
}